odoo/addons/document_page_quality_manual/README.rst
odoo/addons/document_page_quality_manual/__init__.py
odoo/addons/document_page_quality_manual/__manifest__.py
odoo/addons/document_page_quality_manual/data/document_page.xml
odoo/addons/document_page_quality_manual/i18n/ar.po
odoo/addons/document_page_quality_manual/i18n/bg.po
odoo/addons/document_page_quality_manual/i18n/ca.po
odoo/addons/document_page_quality_manual/i18n/cs.po
odoo/addons/document_page_quality_manual/i18n/da.po
odoo/addons/document_page_quality_manual/i18n/de.po
odoo/addons/document_page_quality_manual/i18n/document_page_quality_manual.pot
odoo/addons/document_page_quality_manual/i18n/es.po
odoo/addons/document_page_quality_manual/i18n/es_CR.po
odoo/addons/document_page_quality_manual/i18n/es_MX.po
odoo/addons/document_page_quality_manual/i18n/es_VE.po
odoo/addons/document_page_quality_manual/i18n/fi.po
odoo/addons/document_page_quality_manual/i18n/fr.po
odoo/addons/document_page_quality_manual/i18n/gl.po
odoo/addons/document_page_quality_manual/i18n/hr.po
odoo/addons/document_page_quality_manual/i18n/hu.po
odoo/addons/document_page_quality_manual/i18n/it.po
odoo/addons/document_page_quality_manual/i18n/ja.po
odoo/addons/document_page_quality_manual/i18n/lv.po
odoo/addons/document_page_quality_manual/i18n/mn.po
odoo/addons/document_page_quality_manual/i18n/nb.po
odoo/addons/document_page_quality_manual/i18n/nl.po
odoo/addons/document_page_quality_manual/i18n/oc.po
odoo/addons/document_page_quality_manual/i18n/pt.po
odoo/addons/document_page_quality_manual/i18n/pt_BR.po
odoo/addons/document_page_quality_manual/i18n/ro.po
odoo/addons/document_page_quality_manual/i18n/ru.po
odoo/addons/document_page_quality_manual/i18n/sk.po
odoo/addons/document_page_quality_manual/i18n/sl.po
odoo/addons/document_page_quality_manual/i18n/sr@latin.po
odoo/addons/document_page_quality_manual/i18n/sv.po
odoo/addons/document_page_quality_manual/i18n/tr.po
odoo/addons/document_page_quality_manual/i18n/vi.po
odoo13_addon_document_page_quality_manual-13.0.1.0.1.dev4.dist-info/METADATA
odoo13_addon_document_page_quality_manual-13.0.1.0.1.dev4.dist-info/WHEEL
odoo13_addon_document_page_quality_manual-13.0.1.0.1.dev4.dist-info/top_level.txt
odoo13_addon_document_page_quality_manual-13.0.1.0.1.dev4.dist-info/RECORD
